<?xml version="1.0"?>
<!-- Invoked as: C:\nico\util\lqn\LQN Solvers\lqn2ps.exe -Oxml wbgsql-act-b.lqn -->
<!-- Thu Oct 26 14:45:01 2006 -->

<lqn-model name="wbgsql-act-b" description="Generated by: C:\nico\util\lqn\LQN Solvers\lqn2ps.exe, version 3.10" xmlns:xsi="http://www.w3.org/2001/XMLSchema-instance" xsi:noNamespaceSchemaLocation="file:///C:/Program Files/LQN Solvers/lqn.xsd">
   <solver-params comment="WBG SQL" conv_val="1e-005" it_limit="50" print_int="10" underrelax_coeff="0.9"/>
   <processor name="PClient" multiplicity="100" scheduling="fcfs">
      <task name="Twbgsql2_client" multiplicity="10" scheduling="ref">
         <entry name="Ewbgsql2_client" type="PH1PH2">
            <entry-phase-activities>
               <activity name="Ewbgsql2_client_ph1" phase="1" host-demand-mean="1e-007">
                  <synch-call dest="Ewbgsql2_cpu" calls-mean="1"/>
               </activity>
            </entry-phase-activities>
         </entry>
      </task>
      <task name="Twbgsql_client" multiplicity="10" scheduling="ref">
         <entry name="Ewbgsql_client" type="PH1PH2">
            <entry-phase-activities>
               <activity name="Ewbgsql_client_ph1" phase="1" host-demand-mean="1e-007">
                  <synch-call dest="Ewbgsql_cpu" calls-mean="1"/>
               </activity>
            </entry-phase-activities>
         </entry>
      </task>
   </processor>
   <processor name="PCPU" scheduling="fcfs">
      <task name="Twbgsql_cpu" scheduling="fcfs">
         <entry name="Ewbgsql2_cpu" type="PH1PH2">
            <entry-phase-activities>
               <activity name="Ewbgsql2_cpu_ph1" phase="1" host-demand-mean="0.0019">
                  <synch-call dest="Ewbgsql_disk1" calls-mean="1"/>
               </activity>
            </entry-phase-activities>
         </entry>
         <entry name="Ewbgsql_cpu" type="PH1PH2">
            <entry-phase-activities>
               <activity name="Ewbgsql_cpu_ph1" phase="1" host-demand-mean="0.003">
                  <synch-call dest="Ewbgsql_disk0" calls-mean="1"/>
               </activity>
            </entry-phase-activities>
         </entry>
      </task>
   </processor>
   <processor name="PDisk1" scheduling="fcfs">
      <task name="Twbgsql_disk1" scheduling="fcfs">
         <entry name="Ewbgsql_disk1" type="PH1PH2">
            <entry-phase-activities>
               <activity name="Ewbgsql_disk1_ph1" phase="1" host-demand-mean="0.0001"/>
            </entry-phase-activities>
         </entry>
      </task>
   </processor>
   <processor name="PDisk0" scheduling="fcfs">
      <task name="Twbgsql_disk0" scheduling="fcfs">
         <entry name="Ewbgsql_disk0" type="PH1PH2">
            <entry-phase-activities>
               <activity name="Ewbgsql_disk0_ph1" phase="1" host-demand-mean="0.0001"/>
            </entry-phase-activities>
         </entry>
      </task>
   </processor>
</lqn-model>
